lab5/3/orgatefinal.v
module decodergate(i, o);
  input [3:0] i;
  output reg [15:0] o;

  always @(*)
  begin
    case(i)
      4'b0000: o = 16'd1;
      4'b0001: o = 16'd2;
      4'b0010: o = 16'd4;
      4'b0011: o = 16'd8;
      4'b0100: o = 16'd16;
      4'b0101: o = 16'd32;
      4'b0110: o = 16'd64;
      4'b0111: o = 16'd128;
      4'b1000: o = 16'd256;
      4'b1001: o = 16'd512;
      4'b1010: o = 16'd1024;
      4'b1011: o = 16'd2048;
      4'b1100: o = 16'd4096;
      4'b1101: o = 16'd8192;
      4'b1110: o = 16'd16384;
      4'b1111: o = 16'd32768;
      default: o = 16'd0;
    endcase
  end
endmodule

module orgatefinal(in, f);
  input [3:0] in;
  output f;
  wire [15:0] o;

  decodergate dg(in, o);

  assign f = o[2] | o[3] | o[4] | o[5] | o[6] | o[7] | o[10] | o[11] | o[12] | o[15];
endmodule

lab5/3/orgatefinal_tb.v
`timescale 1ns/1ns
`include "orgatefinal.v"

module orgatrfinal_tb;
  reg [3:0] in;
  wire f;

  orgatefinal ogf(in, f);

  initial begin
    $dumpfile("orgatrfinal_tb.vcd");
    $dumpvars(0, orgatrfinal_tb);
  

    in = 4'h0; #20;
    in = 4'h1; #20;
    in = 4'h2; #20;
    in = 4'h3; #20;
    in = 4'h4; #20;
    in = 4'h5; #20;
    in = 4'h6; #20;
    in = 4'h7; #20;
    in = 4'h8; #20;
    in = 4'h9; #20;
    in = 4'hA; #20;
    in = 4'hB; #20;
    in = 4'hC; #20;
    in = 4'hD; #20;
    in = 4'hE; #20;
    in = 4'hF; #20;

    $display("End");
  end
endmodule

lab5/3/orgatrfinal_tb.vcd
$date
	Wed Aug 28 14:59:19 2024
$end
$version
	Icarus Verilog
$end
$timescale
	1ns
$end
$scope module orgatrfinal_tb $end
$var wire 1 ! f $end
$var reg 4 " in [3:0] $end
$scope module ogf $end
$var wire 1 ! f $end
$var wire 4 # in [3:0] $end
$var wire 16 $ o [15:0] $end
$scope module dg $end
$var wire 4 % i [3:0] $end
$var reg 16 & o [15:0] $end
$upscope $end
$upscope $end
$upscope $end
$enddefinitions $end
#0
$dumpvars
b1 &
b0 %
b1 $
b0 #
b0 "
0!
$end
#20
b10 $
b10 &
b1 "
b1 #
b1 %
#40
1!
b100 $
b100 &
b10 "
b10 #
b10 %
#60
b1000 $
b1000 &
b11 "
b11 #
b11 %
#80
b10000 $
b10000 &
b100 "
b100 #
b100 %
#100
b100000 $
b100000 &
b101 "
b101 #
b101 %
#120
b1000000 $
b1000000 &
b110 "
b110 #
b110 %
#140
b10000000 $
b10000000 &
b111 "
b111 #
b111 %
#160
0!
b100000000 $
b100000000 &
b1000 "
b1000 #
b1000 %
#180
b1000000000 $
b1000000000 &
b1001 "
b1001 #
b1001 %
#200
1!
b10000000000 $
b10000000000 &
b1010 "
b1010 #
b1010 %
#220
b100000000000 $
b100000000000 &
b1011 "
b1011 #
b1011 %
#240
b1000000000000 $
b1000000000000 &
b1100 "
b1100 #
b1100 %
#260
0!
b10000000000000 $
b10000000000000 &
b1101 "
b1101 #
b1101 %
#280
b100000000000000 $
b100000000000000 &
b1110 "
b1110 #
b1110 %
#300
1!
b1000000000000000 $
b1000000000000000 &
b1111 "
b1111 #
b1111 %
