lab4/2/decoder4to16.v
module decoder2to4(w,EN,o);
input [1:0]w;
input EN;
output reg [3:0]o;
always @(w,EN)
begin
if(EN==0 && w==0)
o=1;
else if(EN==0 && w==1)
o=2;
else if(EN==0 && w==2)
o=4;
else if(EN==0 &&w ==3)
o=8;
else 
o=0;
end
endmodule


module decoder4to16(w,EN,o);
input [3:0]w;
input EN;
output [15:0]o;
wire [3:0]en;
decoder2to4 d1(w[3:2],EN,en[3:0]);
decoder2to4 d2(w[1:0],en[0],o[3:0]);
decoder2to4 d3(w[1:0],en[1],o[7:4]);
decoder2to4 d4(w[1:0],en[2],o[11:8]);
decoder2to4 d5(w[1:0],en[3],o[15:12]);
endmodule

lab4/2/decoder4to16_tb.v
`timescale 1ns/1ns
`include "decoder4to16.v"
module decoder4to16_tb();
reg [3:0]w;
reg EN;
wire [15:0]o;
decoder4to16 d4to16(w,EN,o);
initial 
begin
$dumpfile("decoder4to16_tb.vcd");
$dumpvars(0,decoder4to16_tb);
EN=1'b0;w=4'b0000;#20;
EN=1'b1;w=4'b0010;#20;
EN=1'b1;w=4'b0111;#20;
EN=1'b1;w=4'b1100;#20;
EN=1'b1;w=4'b0101;#20;
EN=1'b1;w=4'b1111;#20;
EN=1'b1;w=4'b0001;#20;
EN=1'b1;w=4'b1110;#20;
$display("Test complete");
end
endmodule

lab4/2/decoder4to16_tb.vcd
$date
	Sat Aug 31 09:55:25 2024
$end
$version
	Icarus Verilog
$end
$timescale
	1ns
$end
$scope module decoder4to16_tb $end
$var wire 16 ! o [15:0] $end
$var reg 1 " EN $end
$var reg 4 # w [3:0] $end
$scope module d4to16 $end
$var wire 1 " EN $end
$var wire 4 $ w [3:0] $end
$var wire 16 % o [15:0] $end
$var wire 4 & en [3:0] $end
$scope module d1 $end
$var wire 1 " EN $end
$var wire 2 ' w [1:0] $end
$var reg 4 ( o [3:0] $end
$upscope $end
$scope module d2 $end
$var wire 1 ) EN $end
$var wire 2 * w [1:0] $end
$var reg 4 + o [3:0] $end
$upscope $end
$scope module d3 $end
$var wire 1 , EN $end
$var wire 2 - w [1:0] $end
$var reg 4 . o [3:0] $end
$upscope $end
$scope module d4 $end
$var wire 1 / EN $end
$var wire 2 0 w [1:0] $end
$var reg 4 1 o [3:0] $end
$upscope $end
$scope module d5 $end
$var wire 1 2 EN $end
$var wire 2 3 w [1:0] $end
$var reg 4 4 o [3:0] $end
$upscope $end
$upscope $end
$upscope $end
$enddefinitions $end
#0
$dumpvars
b1 4
b0 3
02
b1 1
b0 0
0/
b1 .
b0 -
0,
b0 +
b0 *
1)
b1 (
b0 '
b1 &
b1000100010000 %
b0 $
b0 #
0"
b1000100010000 !
$end
#20
b100 +
b100 .
b100 1
b100010001000100 !
b100010001000100 %
b100 4
0)
b10 *
b10 -
b10 0
b10 3
b0 &
b0 (
b10 #
b10 $
1"
#40
b1000 +
b1000 .
b1000 1
b1000100010001000 !
b1000100010001000 %
b1000 4
b1 '
b11 *
b11 -
b11 0
b11 3
b111 #
b111 $
#60
b1 +
b1 .
b1 1
b1000100010001 !
b1000100010001 %
b1 4
b11 '
b0 *
b0 -
b0 0
b0 3
b1100 #
b1100 $
#80
b10 +
b10 .
b10 1
b10001000100010 !
b10001000100010 %
b10 4
b1 '
b1 *
b1 -
b1 0
b1 3
b101 #
b101 $
#100
b1000 +
b1000 .
b1000 1
b1000100010001000 !
b1000100010001000 %
b1000 4
b11 '
b11 *
b11 -
b11 0
b11 3
b1111 #
b1111 $
#120
b10 +
b10 .
b10 1
b10001000100010 !
b10001000100010 %
b10 4
b0 '
b1 *
b1 -
b1 0
b1 3
b1 #
b1 $
#140
b100 +
b100 .
b100 1
b100010001000100 !
b100010001000100 %
b100 4
b11 '
b10 *
b10 -
b10 0
b10 3
b1110 #
b1110 $
