lab10/synchronous_counter.v
// Module for positive edge triggered JK FF
module jkff (Q, J, K, clear, clk);
    input J, K, clear, clk;
    output reg Q;

    always @(posedge clk or negedge clear) begin
        if (!clear)
            Q <= 0;
        else if (J == 0 && K == 1)
            Q <= 0; // Reset state
        else if (J == 1 && K == 0)
            Q <= 1; // Set state
        else if (J == 1 && K == 1)
            Q <= ~Q; // Toggle state
    end
endmodule

// Synchronous 3-Bit Up Counter using JK FF
module synchronous_counter (clear, clk, Q);
    input clear, clk;
    output [2:0] Q;

    // JK flip-flops connections
    jkff FF0 (Q[0], ~Q[1], 1'b1, clear, clk);            // LSB toggles always (J=K=1)
    jkff FF1 (Q[1], Q[0], ~Q[0], clear, clk);           // Toggles when Q[0] is 1
    jkff FF2 (Q[2], Q[1], Q[1]&(~Q[0]), clear, clk);            // Toggles when Q[1] is 1

endmodule

lab10/synchronous_counter_tb.v
`timescale 1ns/1ns
`include "synchronous_counter.v" // Ensure this file is in the same directory

module synchronous_counter_tb;
    reg clear, clk;
    wire [2:0] Q;

    // Instantiation
    synchronous_counter G0 (clear, clk, Q);

    // Clock generation
    always #5 clk = ~clk;

    initial begin
        clear = 0;
        clk = 1;
        #12 clear = 1; // Release clear after some time
        #150 $finish;   // Finish simulation after 150 time units
    end

    initial begin
        $dumpfile("synchronous_counter_tb.vcd");
        $dumpvars(0, synchronous_counter_tb);
        $monitor($time, " clear=%b, Q=%3b", clear, Q);
    end
endmodule

lab10/synchronous_counter_tb.vcd
$date
	Wed Oct 23 16:07:49 2024
$end
$version
	Icarus Verilog
$end
$timescale
	1ns
$end
$scope module synchronous_counter_tb $end
$var wire 3 ! Q [2:0] $end
$var reg 1 " clear $end
$var reg 1 # clk $end
$scope module G0 $end
$var wire 1 " clear $end
$var wire 1 # clk $end
$var wire 3 $ Q [2:0] $end
$scope module FF0 $end
$var wire 1 % J $end
$var wire 1 & K $end
$var wire 1 " clear $end
$var wire 1 # clk $end
$var reg 1 ' Q $end
$upscope $end
$scope module FF1 $end
$var wire 1 ( J $end
$var wire 1 ) K $end
$var wire 1 " clear $end
$var wire 1 # clk $end
$var reg 1 * Q $end
$upscope $end
$scope module FF2 $end
$var wire 1 + J $end
$var wire 1 , K $end
$var wire 1 " clear $end
$var wire 1 # clk $end
$var reg 1 - Q $end
$upscope $end
$upscope $end
$upscope $end
$enddefinitions $end
#0
$dumpvars
0-
0,
0+
0*
1)
0(
0'
1&
1%
b0 $
1#
0"
b0 !
$end
#5
0#
#10
1#
#12
1"
#15
0#
#20
0)
1(
b1 !
b1 $
1'
1#
#25
0#
#30
1,
0%
1)
1+
0(
1*
b10 !
b10 $
0'
1#
#35
0#
#40
0,
1%
0+
0*
b100 !
b100 $
1-
1#
#45
0#
#50
0)
1(
b101 !
b101 $
1'
1#
#55
0#
#60
1,
1)
0%
0(
1+
0'
b110 !
b110 $
1*
1#
#65
0#
#70
0,
1%
0+
0-
b0 !
b0 $
0*
1#
#75
0#
#80
0)
1(
b1 !
b1 $
1'
1#
#85
0#
#90
1,
0%
1)
1+
0(
1*
b10 !
b10 $
0'
1#
#95
0#
#100
0,
1%
0+
0*
b100 !
b100 $
1-
1#
#105
0#
#110
0)
1(
b101 !
b101 $
1'
1#
#115
0#
#120
1,
1)
0%
0(
1+
0'
b110 !
b110 $
1*
1#
#125
0#
#130
0,
1%
0+
0-
b0 !
b0 $
0*
1#
#135
0#
#140
0)
1(
b1 !
b1 $
1'
1#
#145
0#
#150
1,
0%
1)
1+
0(
1*
b10 !
b10 $
0'
1#
#155
0#
#160
0,
1%
0+
0*
b100 !
b100 $
1-
1#
