lab6/4/srff.v
module srff(sr,clk,reset,q);
input [1:0]sr;
input clk,reset;
output reg q=0;
always @(negedge clk or negedge reset)
begin
if(!reset)
q<=0;
else
case(sr)
2'b00:q<=q;
2'b01:q<=0;
2'b10:q<=1;
2'b11:q<=1'bx;
default:q<=q;
endcase
end
endmodule

lab6/4/srff_tb.v
`timescale 1ns/1ns
`include "srff.v"
module srff_tb();
reg clk,reset;
reg [1:0]sr;
wire q;
srff ab(sr,clk,reset,q);
initial begin
$dumpfile ("srff_tb.vcd");
$dumpvars(0,srff_tb);
end
initial begin
clk=0;
forever #20 clk=~clk;
end
initial begin
sr=2'b00;reset=1;#20;
sr=2'b01;reset=1;#20;
sr=2'b11;reset=1;#20;
sr=2'b10;reset=1;#20;
sr=2'b00;reset=0;#20;
sr=2'b11;reset=0;#20;
sr=2'b11;reset=1;#20;
sr=2'b01;reset=1;#20;
sr=2'b11;reset=1;#20;
sr=2'b10;reset=1;#20;
#200 
$display("DONE");
$finish;
end 
endmodule

lab6/4/srff_tb.vcd
$date
	Sat Sep 14 10:14:09 2024
$end
$version
	Icarus Verilog
$end
$timescale
	1ns
$end
$scope module srff_tb $end
$var wire 1 ! q $end
$var reg 1 " clk $end
$var reg 1 # reset $end
$var reg 2 $ sr [1:0] $end
$scope module ab $end
$var wire 1 " clk $end
$var wire 1 # reset $end
$var wire 2 % sr [1:0] $end
$var reg 1 ! q $end
$upscope $end
$upscope $end
$enddefinitions $end
#0
$dumpvars
b0 %
b0 $
1#
0"
0!
$end
#20
b1 $
b1 %
1"
#40
x!
b11 $
b11 %
0"
#60
b10 $
b10 %
1"
#80
0!
0#
b0 $
b0 %
0"
#100
b11 $
b11 %
1"
#120
x!
1#
0"
#140
b1 $
b1 %
1"
#160
b11 $
b11 %
0"
#180
b10 $
b10 %
1"
#200
1!
0"
