lab6/1/dff.v
module dff(D,clk,reset,Q);
input D,clk,reset;
output reg Q=0;
always @(posedge clk)
begin
if(reset)
Q<=0;
else
Q<=D;
end
endmodule

lab6/1/dff_tb.v
`timescale 1ns/1ns
`include "dff.v"


module dff_tb();
    reg D, clk, reset;
    wire Q;

    dff ab (D,clk,reset,Q);

    initial begin
        clk = 0;
        forever #20 clk = ~clk;  
    end
    initial begin
        $dumpfile("dff_tb.vcd");
        $dumpvars(0, dff_tb);
    end

    initial begin
        D = 0; reset = 0;
        #20;
        D = 1; reset = 0;
        #20;
        D = 0; reset = 0;
        #20;
        D = 1; reset = 0;
        #20;
        D = 0; reset = 0;
        #20;
        D = 1; reset = 1; 
        #20;
        D = 1; reset = 0; 
        #20;
        D = 1; reset = 0;
        #160;

        $display("DONE");
        $finish;
    end
endmodule

lab6/1/dff_tb.vcd
$date
	Sat Sep 14 09:23:31 2024
$end
$version
	Icarus Verilog
$end
$timescale
	1ns
$end
$scope module dff_tb $end
$var wire 1 ! Q $end
$var reg 1 " D $end
$var reg 1 # clk $end
$var reg 1 $ reset $end
$scope module ab $end
$var wire 1 " D $end
$var wire 1 # clk $end
$var wire 1 $ reset $end
$var reg 1 ! Q $end
$upscope $end
$upscope $end
$enddefinitions $end
#0
$dumpvars
0$
0#
0"
0!
$end
#20
1!
1"
1#
#40
0"
0#
#60
1"
1#
#80
0"
0#
#100
0!
1$
1"
1#
#120
0$
0#
#140
1!
1#
