lab3/1/mux4to1.v
module mux4to1(w0,w1,w2,w3,S,f);
	input w0,w1,w2,w3;
	input [1:0]S;
	output reg f;
	
	
	always @(w0 or w1 or w2 or w3 or S) begin
        if (S == 2'b00)
            f = w0;
        else if (S == 2'b01)
            f = w1;
        else if (S == 2'b10)
            f = w2;
        else if (S == 2'b11)
            f = w3;
        else
            f = 1'b0;
           
	end
     endmodule

lab3/1/mux4to1_tb.v
`timescale 1ns/1ns
`include "mux4to1.v"

module mux4to1_tb();
    reg w0, w1, w2, w3;
    reg [1:0] S;
    wire f;
    mux4to1 mx4t1(w0,w1,w2,w3,S,f);
    initial 
    begin
        $dumpfile("mux4to1_tb.vcd");
        $dumpvars(0, mux4to1_tb);
        w0 = 0; w1 = 0; w2 = 0; w3 = 0; S = 2'b00;
        #10;

        w0 = 0; w1 = 1; w2 = 0; w3 = 0; S = 2'b01;
        #10;

        w0 = 0; w1 = 0; w2 = 1; w3 = 0; S = 2'b10;
        #10;

        w0 = 0; w1 = 0; w2 = 0; w3 = 1; S = 2'b11;
        #10;

        w0 = 1; w1 = 0; w2 = 0; w3 = 0; S = 2'b00;
        #10;

        w0 = 0; w1 = 1; w2 = 0; w3 = 0; S = 2'b01;
        #10;

        w0 = 0; w1 = 0; w2 = 1; w3 = 0; S = 2'b10;
        #10;

        w0 = 0; w1 = 0; w2 = 0; w3 = 1; S = 2'b11;
        #10;

        $display("Test Complete");
    end
endmodule

lab3/1/mux4to1_tb.vcd
$date
	Sat Aug 24 09:48:56 2024
$end
$version
	Icarus Verilog
$end
$timescale
	1ns
$end
$scope module mux4to1_tb $end
$var wire 1 ! f $end
$var reg 2 " S [1:0] $end
$var reg 1 # w0 $end
$var reg 1 $ w1 $end
$var reg 1 % w2 $end
$var reg 1 & w3 $end
$scope module mx4t1 $end
$var wire 2 ' S [1:0] $end
$var wire 1 # w0 $end
$var wire 1 $ w1 $end
$var wire 1 % w2 $end
$var wire 1 & w3 $end
$var reg 1 ! f $end
$upscope $end
$upscope $end
$enddefinitions $end
#0
$dumpvars
b0 '
0&
0%
0$
0#
b0 "
0!
$end
#10
1!
b1 "
b1 '
1$
#20
b10 "
b10 '
1%
0$
#30
b11 "
b11 '
1&
0%
#40
b0 "
b0 '
0&
1#
#50
b1 "
b1 '
1$
0#
#60
b10 "
b10 '
1%
0$
#70
b11 "
b11 '
1&
0%
