examprep/1/example.v
module example(x1,x2,x3,x4,f);
	input x1,x2,x3,x4;
	output f;
	assign f = (x3 & ~x4)|(x2 & ~x3);
endmodule

examprep/example_tb.v
`timescale 1ns/1ns
`include "example.v"


module example_tb();
	reg x1,x2,x3,x4;
	wire f;
	example ex(x1,x2,x3,x4,f);
	initial
	begin
			$dumpfile("example_tb.vcd");
			$dumpvars(0,example_tb);
			
			x1=1'b0; x2=1'b0; x3=1'b0;x4 = 1'b0;
			#20;
			x1=1'b0; x2=1'b0; x3=1'b1;x4 = 1'b1;
			#20;
			x1=1'b0; x2=1'b1; x3=1'b0;x4 = 1'b0;
			#20;
			x1=1'b0; x2=1'b1; x3=1'b1;x4 = 1'b1;
			#20;
			x1=1'b1; x2=1'b0; x3=1'b0;x4 = 1'b0;
			#20;
			x1=1'b1; x2=1'b0; x3=1'b1;x4 = 1'b1;
			#20;
			x1=1'b1; x2=1'b1; x3=1'b0;x4 = 1'b0;
			#20;
			x1=1'b1; x2=1'b1; x3=1'b1;x4 = 1'b1;
			#20;
			
			$display("Test complete");
end 
endmodule

examprep/1/example_tb.vcd
$date
	Mon Oct 14 09:32:19 2024
$end
$version
	Icarus Verilog
$end
$timescale
	1ns
$end
$scope module example_tb $end
$var wire 1 ! f $end
$var reg 1 " x1 $end
$var reg 1 # x2 $end
$var reg 1 $ x3 $end
$var reg 1 % x4 $end
$scope module ex $end
$var wire 1 ! f $end
$var wire 1 " x1 $end
$var wire 1 # x2 $end
$var wire 1 $ x3 $end
$var wire 1 % x4 $end
$upscope $end
$upscope $end
$enddefinitions $end
#0
$dumpvars
0%
0$
0#
0"
0!
$end
#20
0!
1%
1$
#40
1!
0%
0$
1#
#60
0!
1%
1$
#80
0%
0$
0#
1"
#100
0!
1%
1$
#120
1!
0%
0$
1#
#140
0!
1%
1$
