lab 7/prog 3/jkff.v
module jkff(jk,clk,reset,q);
input [1:0]jk;
input clk,reset;
output reg q=0;
always @(posedge clk or posedge reset)
begin
if(reset)
q<=0;
else
case(jk)
2'b00:q<=q;
2'b01:q<=0;
2'b10:q<=1;
2'b11:q<=~q;
default:q<=q;
endcase
end
endmodule

lab 7/prog 3/jkff_tb.v
`timescale 1ns/1ns
`include "jkff.v"
module jkff_tb();
reg[1:0]jk;
reg clk,reset;
wire q;
jkff ab(jk,clk,reset,q);
initial begin
$dumpfile("jkff_tb.vcd");
$dumpvars(0,jkff_tb);
end
initial begin
clk=0;
forever #20 clk=~clk;
end
    initial begin
        jk = 2'b00; reset = 0; #20;
        jk = 2'b01; reset = 0; #20;
        jk = 2'b10; reset = 0; #20;
        jk = 2'b11; reset = 0; #20;
        jk = 2'b00; reset = 1; #20;
        jk = 2'b11; reset = 1; #20;
        jk = 2'b01; reset = 0; #20;
        jk = 2'b10; reset = 0; #20;
        jk = 2'b11; reset = 0; #20;
        jk = 2'b01; reset = 0; #20;
        #220;

        $display("DONE");
        $finish;
    end
endmodule

lab 7/prog 3/jkff_tb.vcd
$date
	Wed Sep  4 15:19:40 2024
$end
$version
	Icarus Verilog
$end
$timescale
	1ns
$end
$scope module jkff_tb $end
$var wire 1 ! q $end
$var reg 1 " clk $end
$var reg 2 # jk [1:0] $end
$var reg 1 $ reset $end
$scope module ab $end
$var wire 1 " clk $end
$var wire 2 % jk [1:0] $end
$var wire 1 $ reset $end
$var reg 1 ! q $end
$upscope $end
$upscope $end
$enddefinitions $end
#0
$dumpvars
b0 %
0$
b0 #
0"
0!
$end
#20
b1 #
b1 %
1"
#40
b10 #
b10 %
0"
#60
1!
b11 #
b11 %
1"
#80
0!
1$
b0 #
b0 %
0"
#100
b11 #
b11 %
1"
#120
0$
b1 #
b1 %
0"
#140
1!
b10 #
b10 %
1"
#160
b11 #
b11 %
0"
#180
0!
b1 #
b1 %
1"
