lab4/1/decoder2to4.v
module decoder2to4(w,en,o);
input [1:0]w;
input en;
output reg [3:0]o;
always @(w,en)
begin
if(en==0 && w==0)
o=1;
else if(en==0 && w==1)
o=2;
else if(en==0 && w==2)
o=4;
else if(en==0 &&w ==3)
o=8;
else 
o=0;
end
endmodule

lab4/1/decoder2to4_tb.v
`timescale 1ns/1ns
`include "decoder2to4.v"
module decoder2to4_tb();
reg [1:0]w;
reg en;
wire [3:0]op;
decoder2to4 d2t4(w,en,op);
initial
begin
$dumpfile("decoder2to4_tb.vcd");
$dumpvars(0,decoder2to4_tb);
en=1'b0;w=2'b00;#20;
en=1'b0;w=2'b01;#20;
en=1'b0;w=2'b10;#20;
en=1'b0;w=2'b11;#20;
en=1'b1;w=2'b00;#20;
en=1'b1;w=2'b01;#20;
en=1'b1;w=2'b10;#20;
en=1'b1;w=2'b11;#20;
$display("Test complete");
end
endmodule

lab4/1/decoder2to4_tb.vcd
$date
	Sat Aug 31 09:33:04 2024
$end
$version
	Icarus Verilog
$end
$timescale
	1ns
$end
$scope module decoder2to4_tb $end
$var wire 4 ! op [3:0] $end
$var reg 1 " en $end
$var reg 2 # w [1:0] $end
$scope module d2t4 $end
$var wire 1 " en $end
$var wire 2 $ w [1:0] $end
$var reg 4 % o [3:0] $end
$upscope $end
$upscope $end
$enddefinitions $end
#0
$dumpvars
b1 %
b0 $
b0 #
0"
b1 !
$end
#20
b10 !
b10 %
b1 #
b1 $
#40
b100 !
b100 %
b10 #
b10 $
#60
b1000 !
b1000 %
b11 #
b11 $
#80
b0 !
b0 %
b0 #
b0 $
1"
#100
b1 #
b1 $
#120
b10 #
b10 $
#140
b11 #
b11 $
