lab9/synchronous_counter.v
// Module for positive edge triggered T FF
module tff (Q, T, clear, clk);
    input T, clear, clk;
    output reg Q;

    always @(posedge clk or negedge clear) begin
        if (!clear)
            Q <= 0;
        else if (T)
            Q <= ~Q; // Toggle if T is high
    end
endmodule

// Synchronous 3-Bit Up Counter using T FF
module synchronous_counter (clear, clk, Q);
    input clear, clk;
    output [2:0] Q;

    wire w1, w2;

    // T Flip-Flops connections for up counting
    tff FF0 (Q[0], 1'b1, clear, clk);        // LSB toggles always
    tff FF1 (Q[1], Q[0], clear, clk);        // Toggles when Q[0] is 1
    tff FF2 (Q[2], Q[1], clear, clk);        // Toggles when Q[1] is 1

endmodule

lab9/synchronous_counter_test.v
`timescale 1ns/1ns
`include "synchronous_counter.v"
//Name of the Verilog file
module synchronous_counter_test ;
reg clear, clk;
wire [2:0] Q;
// Instanstiation
synchronous_counter G0 (clear, clk, Q);
always #5 clk=~clk;
initial
begin
clear=0;
clk=1;
#150 $finish;
end
initial
begin
$dumpfile("synchronous_counter.vcd");
$dumpvars(0,synchronous_counter_test);
$monitor($time, " clear=%b, Q=%3b", clear, Q );
#12 clear =1;
end
endmodule

lab9/synchronous_counter.vcd
$date
	Wed Oct 23 15:58:06 2024
$end
$version
	Icarus Verilog
$end
$timescale
	1ns
$end
$scope module synchronous_counter_test $end
$var wire 3 ! Q [2:0] $end
$var reg 1 " clear $end
$var reg 1 # clk $end
$scope module G0 $end
$var wire 1 " clear $end
$var wire 1 # clk $end
$var wire 3 $ Q [2:0] $end
$scope module FF0 $end
$var wire 1 % T $end
$var wire 1 " clear $end
$var wire 1 # clk $end
$var reg 1 & Q $end
$upscope $end
$scope module FF1 $end
$var wire 1 ' T $end
$var wire 1 " clear $end
$var wire 1 # clk $end
$var reg 1 ( Q $end
$upscope $end
$scope module FF2 $end
$var wire 1 ) T $end
$var wire 1 " clear $end
$var wire 1 # clk $end
$var reg 1 * Q $end
$upscope $end
$upscope $end
$upscope $end
$enddefinitions $end
#0
$dumpvars
0*
0)
0(
0'
0&
1%
b0 $
1#
0"
b0 !
$end
#5
0#
#10
1#
#12
1"
#15
0#
#20
1'
b1 !
b1 $
1&
1#
#25
0#
#30
1)
0'
1(
b10 !
b10 $
0&
1#
#35
0#
#40
1'
1&
b111 !
b111 $
1*
1#
#45
0#
#50
0)
0'
0*
0(
b0 !
b0 $
0&
1#
#55
0#
#60
1'
b1 !
b1 $
1&
1#
#65
0#
#70
1)
0'
1(
b10 !
b10 $
0&
1#
#75
0#
#80
1'
1&
b111 !
b111 $
1*
1#
#85
0#
#90
0)
0'
0*
0(
b0 !
b0 $
0&
1#
#95
0#
#100
1'
b1 !
b1 $
1&
1#
#105
0#
#110
1)
0'
1(
b10 !
b10 $
0&
1#
#115
0#
#120
1'
1&
b111 !
b111 $
1*
1#
#125
0#
#130
0)
0'
0*
0(
b0 !
b0 $
0&
1#
#135
0#
#140
1'
b1 !
b1 $
1&
1#
#145
0#
#150
1)
0'
1(
b10 !
b10 $
0&
1#
