lab1/question2.v
module question2(A,B,C,D,f);
input A,B,C,D;
output f;
assign f =  (C&~D)|(~A&~D)|(B&~D)|(~A&B&C);
endmodule

lab1/question2_tb.v
`timescale 1ns/1ns
`include "question2.v" //Name of the Verilog file
module question2_tb();
reg A,B,C,D;
wire f;
question2 q2(A,B,C,D,f); //Instantiation of the module
initial
begin
	$dumpfile("question2_tb.vcd");
	$dumpvars(0, question2_tb);
	A =1'b0;B = 1'b0;C =1'b0;D= 1'b0;
	#20;
	A =1'b0;B = 1'b0;C =1'b0;D= 1'b1;
	#20;
	A =1'b0;B = 1'b0;C =1'b1;D= 1'b0;
	#20;
	A =1'b0;B = 1'b0;C =1'b1;D= 1'b1;
	#20;
	A =1'b0;B = 1'b1;C =1'b0;D= 1'b0;
	#20;
	A =1'b0;B = 1'b1;C =1'b0;D= 1'b1;
	#20;
	A =1'b0;B = 1'b1;C =1'b1;D= 1'b0;
	#20;
	A =1'b0;B = 1'b1;C =1'b1;D= 1'b1;
	#20;
	A =1'b1;B = 1'b0;C =1'b0;D= 1'b0;
	#20;
	A =1'b1;B = 1'b0;C =1'b0;D= 1'b1;
	#20;
	A =1'b1;B = 1'b0;C =1'b1;D= 1'b0;
	#20;
	A =1'b1;B = 1'b0;C =1'b1;D= 1'b1;
	#20;
	A =1'b1;B = 1'b1;C =1'b0;D= 1'b0;
	#20;
	A =1'b1;B = 1'b1;C =1'b0;D= 1'b1;
	#20;
	A =1'b1;B = 1'b1;C =1'b1;D= 1'b0;
	#20;
	A =1'b1;B = 1'b1;C =1'b1;D= 1'b1;
	#20;
	$display("Test complete");
end
endmodule

lab1/question2_tb.vcd
$date
	Sat Aug  3 10:33:07 2024
$end
$version
	Icarus Verilog
$end
$timescale
	1ns
$end
$scope module question2_tb $end
$var wire 1 ! f $end
$var reg 1 " A $end
$var reg 1 # B $end
$var reg 1 $ C $end
$var reg 1 % D $end
$scope module q2 $end
$var wire 1 " A $end
$var wire 1 # B $end
$var wire 1 $ C $end
$var wire 1 % D $end
$var wire 1 ! f $end
$upscope $end
$upscope $end
$enddefinitions $end
#0
$dumpvars
0%
0$
0#
0"
1!
$end
#20
0!
1%
#40
1!
0%
1$
#60
0!
1%
#80
1!
0%
0$
1#
#100
0!
1%
#120
1!
0%
1$
#140
1%
#160
0!
0%
0$
0#
1"
#180
1%
#200
1!
0%
1$
#220
0!
1%
#240
1!
0%
0$
1#
#260
0!
1%
#280
1!
0%
1$
#300
0!
1%
